odoo/addons/budget_control_purchase/README.rst
odoo/addons/budget_control_purchase/__init__.py
odoo/addons/budget_control_purchase/__manifest__.py
odoo/addons/budget_control_purchase/models/__init__.py
odoo/addons/budget_control_purchase/models/account_budget_move.py
odoo/addons/budget_control_purchase/models/account_move.py
odoo/addons/budget_control_purchase/models/account_move_line.py
odoo/addons/budget_control_purchase/models/budget_commit_forward.py
odoo/addons/budget_control_purchase/models/budget_control.py
odoo/addons/budget_control_purchase/models/budget_period.py
odoo/addons/budget_control_purchase/models/purchase.py
odoo/addons/budget_control_purchase/models/purchase_budget_move.py
odoo/addons/budget_control_purchase/readme/CONTRIBUTORS.md
odoo/addons/budget_control_purchase/readme/DESCRIPTION.md
odoo/addons/budget_control_purchase/report/__init__.py
odoo/addons/budget_control_purchase/report/budget_common_monitoring.py
odoo/addons/budget_control_purchase/report/budget_monitor_report.py
odoo/addons/budget_control_purchase/security/ir.model.access.csv
odoo/addons/budget_control_purchase/static/description/icon.png
odoo/addons/budget_control_purchase/static/description/index.html
odoo/addons/budget_control_purchase/tests/__init__.py
odoo/addons/budget_control_purchase/tests/test_budget_purchase.py
odoo/addons/budget_control_purchase/views/budget_commit_forward_view.xml
odoo/addons/budget_control_purchase/views/budget_control_view.xml
odoo/addons/budget_control_purchase/views/budget_period_view.xml
odoo/addons/budget_control_purchase/views/purchase_budget_move.xml
odoo/addons/budget_control_purchase/views/purchase_view.xml
odoo_addon_budget_control_purchase-18.0.1.2.1.dist-info/METADATA
odoo_addon_budget_control_purchase-18.0.1.2.1.dist-info/WHEEL
odoo_addon_budget_control_purchase-18.0.1.2.1.dist-info/top_level.txt
odoo_addon_budget_control_purchase-18.0.1.2.1.dist-info/RECORD
